rainbow4th/__init__.py
tests/__init__.py
tests/test_rainbow4th.py
RAINBOW4TH-0.0.42.dist-info/LICENSE.md
RAINBOW4TH-0.0.42.dist-info/METADATA
RAINBOW4TH-0.0.42.dist-info/WHEEL
RAINBOW4TH-0.0.42.dist-info/top_level.txt
RAINBOW4TH-0.0.42.dist-info/RECORD
