Metadata-Version: 2.1
Name: RAINBOW4TH
Version: 0.0.42
Summary: RAINBOW4TH is a C++/Python/Java14 Powered FORTH Environment Bundled with SQLite/PostgreSQL/libcurl Plus More Built In and Multiple IDEs. Its derived from and feed backs to DOLPHIN RETROFORH.
Home-page: https://rainbow4th.readme.io
Author: Scott McCallum (https github.com scott91e1)
Author-email: 262464@195387.com
License: UNKNOWN
Platform: UNKNOWN
Classifier: Programming Language :: Python :: 3
Classifier: License :: OSI Approved :: MIT License
Classifier: Operating System :: OS Independent
Requires-Python: >=3.6
